<?xml version='1.0' encoding='utf-8'?>
<job-scheduling-data>
    <schedule>
        <job>
            <name>DoraApiHealthCheckJob</name>
            <job-class>gov.ca.cwds.jobs.DoraApiHealthCheckJob</job-class>
        </job>
        <trigger>
            <cron>
                <name>DoraApiHealthCheckJob-Trigger</name>
                <job-name>DoraApiHealthCheckJob</job-name>
                <cron-expression>0 */10 * * * ?</cron-expression>
            </cron>
        </trigger>
    </schedule>
</job-scheduling-data>